aind_behavior_video_transformation/__init__.py
aind_behavior_video_transformation/etl.py
aind_behavior_video_transformation/filesystem.py
aind_behavior_video_transformation/transform_videos.py
aind_behavior_video_transformation-0.2.2.dist-info/licenses/LICENSE
aind_behavior_video_transformation-0.2.2.dist-info/METADATA
aind_behavior_video_transformation-0.2.2.dist-info/WHEEL
aind_behavior_video_transformation-0.2.2.dist-info/top_level.txt
aind_behavior_video_transformation-0.2.2.dist-info/RECORD
