Metadata-Version: 2.4
Name: aind-behavior-video-transformation
Version: 0.2.2
Summary: Handles behavior modality folder
Author: Allen Institute for Neural Dynamics
License: MIT
Classifier: Programming Language :: Python :: 3
Requires-Python: >=3.10
License-File: LICENSE
Requires-Dist: aind-data-transformation>=0.1.0
Provides-Extra: dev
Requires-Dist: black; extra == "dev"
Requires-Dist: coverage; extra == "dev"
Requires-Dist: flake8; extra == "dev"
Requires-Dist: interrogate; extra == "dev"
Requires-Dist: isort; extra == "dev"
Requires-Dist: Sphinx; extra == "dev"
Requires-Dist: furo; extra == "dev"
Dynamic: license-file
